cImage.py
thonny_cImage-1.4.2.dist-info/DESCRIPTION.rst
thonny_cImage-1.4.2.dist-info/METADATA
thonny_cImage-1.4.2.dist-info/RECORD
thonny_cImage-1.4.2.dist-info/WHEEL
thonny_cImage-1.4.2.dist-info/metadata.json
thonny_cImage-1.4.2.dist-info/top_level.txt
